chump/__init__.py
chump/connection_pool.py
chump-1.6.0.dist-info/METADATA
chump-1.6.0.dist-info/RECORD
chump-1.6.0.dist-info/WHEEL
chump-1.6.0.dist-info/top_level.txt
