Metadata-Version: 2.1
Name: chump
Version: 1.6.0
Summary: A fully featured API wrapper for Pushover.
Home-page: https://github.com/karanlyons/chump
Author: Karan Lyons
Author-email: karan@karanlyons.com
License: Apache 2.0
Project-URL: Source, https://github.com/karanlyons/chump
Project-URL: Documentation, https://chump.readthedocs.io
Project-URL: Tracker, https://github.com/karanlyons/chump/issues
Keywords: pushover api push notifications
Platform: UNKNOWN
Classifier: Development Status :: 5 - Production/Stable
Classifier: Intended Audience :: Developers
Classifier: Natural Language :: English
Classifier: License :: OSI Approved :: Apache Software License
Classifier: Programming Language :: Python
Classifier: Programming Language :: Python :: 2
Classifier: Programming Language :: Python :: 2.7
Classifier: Programming Language :: Python :: 3
Classifier: Programming Language :: Python :: 3.0
Classifier: Programming Language :: Python :: 3.1
Classifier: Programming Language :: Python :: 3.2
Classifier: Programming Language :: Python :: 3.3
Classifier: Programming Language :: Python :: 3.4
Classifier: Programming Language :: Python :: 3.5
Classifier: Programming Language :: Python :: 3.6
Classifier: Programming Language :: Python :: 3.7
Classifier: Programming Language :: Python :: Implementation :: CPython
Classifier: Programming Language :: Python :: Implementation :: PyPy
Requires-Python: >=2.7
